helperLTE/__init__.py
helperLTE/helperLTE.py
helperLTE-0.1.0.dist-info/METADATA
helperLTE-0.1.0.dist-info/WHEEL
helperLTE-0.1.0.dist-info/top_level.txt
helperLTE-0.1.0.dist-info/RECORD
