Metadata-Version: 2.1
Name: helperLTE
Version: 0.1.0
Summary: This is a utility library for ML tasks including image processing and model training.
Home-page: https://github.com/bahramzada/helperfunctions
Author: bahramzada
Author-email: raulbahramzada@gmail.com
Classifier: Programming Language :: Python :: 3
Classifier: License :: OSI Approved :: MIT License
Classifier: Operating System :: OS Independent
Requires-Python: >=3.8
Requires-Dist: numpy
Requires-Dist: torch>=1.8.0
Requires-Dist: torchvision>=0.9.0
Requires-Dist: tqdm
